EasyMLLib/CSVWriter.py
EasyMLLib/DataGatherer.py
EasyMLLib/DataSplitter.py
EasyMLLib/ModelSaver.py
EasyMLLib/__init__.py
EasyMLLib/helper.py
EasyMLLib/logger.py
EasyMLLib/TestScripts/__init__.py
EasyMLLib/TestScripts/useful/__init__.py
EasyMLLib/TestScripts/useful/testFeatures.py
EasyMLLib/TestScripts/useful/testModels.py
EasyMLLIB-0.1.2.dist-info/METADATA
EasyMLLIB-0.1.2.dist-info/WHEEL
EasyMLLIB-0.1.2.dist-info/top_level.txt
EasyMLLIB-0.1.2.dist-info/RECORD
